python_easy_json/__init__.py
python_easy_json/json_object.py
python_easy_json-1.2.4.dist-info/licenses/LICENSE
python_easy_json-1.2.4.dist-info/METADATA
python_easy_json-1.2.4.dist-info/WHEEL
python_easy_json-1.2.4.dist-info/top_level.txt
python_easy_json-1.2.4.dist-info/RECORD
