Metadata-Version: 2.4
Name: python-easy-json
Version: 1.2.4
Summary: A simple, yet powerful, JSON/python dictionary to object deserialization
Author-email: Robert Abram <rabram991@gmail.com>
License-Expression: MIT
Project-URL: Homepage, https://github.com/robabram/python-easy-json
Project-URL: Repository, https://github.com/robabram/python-easy-json
Project-URL: Changelog, https://github.com/robabram/python-easy-json
Project-URL: Issues, https://github.com/robabram/python-easy-json/issues
Keywords: serialization,rest,json,api,marshal,marshalling,deserialization,schema,model,models,data
Classifier: Development Status :: 5 - Production/Stable
Classifier: Intended Audience :: Developers
Classifier: Programming Language :: Python :: 3
Classifier: Programming Language :: Python :: 3.9
Classifier: Programming Language :: Python :: 3.10
Classifier: Programming Language :: Python :: 3.11
Classifier: Programming Language :: Python :: 3.12
Classifier: Programming Language :: Python :: 3.13
Classifier: Programming Language :: Python :: 3.14
Requires-Python: >=3.9
License-File: LICENSE
Requires-Dist: dateutils
Dynamic: license-file
